README.rst
setup.py
fclear/__init__.py
fclear/cleaner.py
fclear/cli.py
fclear/exception.py
fclear.egg-info/PKG-INFO
fclear.egg-info/SOURCES.txt
fclear.egg-info/dependency_links.txt
fclear.egg-info/entry_points.txt
fclear.egg-info/top_level.txt